model_logger/__init__.py
model_logger/apps.py
model_logger/decorators.py
model_logger/models.py
model_logger/migrations/0001_initial.py
model_logger/migrations/__init__.py
django_logging_easy-0.2.dist-info/LICENSE
django_logging_easy-0.2.dist-info/METADATA
django_logging_easy-0.2.dist-info/WHEEL
django_logging_easy-0.2.dist-info/top_level.txt
django_logging_easy-0.2.dist-info/RECORD
