Metadata-Version: 2.1
Name: django-logging-easy
Version: 0.2
Summary: A Django app to log model changes
Home-page: https://github.com/hasan-furkan/django-model-logger
Author: Hasan Furkan
Author-email: hsnfrkn32@gmail.com
License: MIT
Classifier: Environment :: Web Environment
Classifier: Framework :: Django
Classifier: Framework :: Django :: 3.2
Classifier: Intended Audience :: Developers
Classifier: License :: OSI Approved :: MIT License
Classifier: Operating System :: OS Independent
Classifier: Programming Language :: Python
Classifier: Programming Language :: Python :: 3
Classifier: Programming Language :: Python :: 3.6
Classifier: Topic :: Internet :: WWW/HTTP
License-File: LICENSE
Requires-Dist: Django >=3.2
